src/design/adder_submodule.sv
module adder_submodule (
    input logic clk,              
    input logic reset,           
    input logic [11:0] number1, 
    input logic [11:0] number2,
    input logic enable, 
    output logic [11:0] sum_result, //Resultado de la suma
    output logic sum_state          //Estado de la suma (finalizada o no)
);

    logic [13:0] sum_reg;
    logic sum_ready;

    always_ff @(posedge clk, posedge reset) begin
        if (reset) begin
            sum_reg <= 14'd0;
            sum_ready <= 1'b0;
        end else if (enable) begin
            sum_reg <= number1 + number2;
            sum_ready <= 1'b1;
        end else begin
            sum_ready <= 1'b0;
        end
    end

    assign sum_result = sum_reg;
    assign sum_state = sum_ready;
    
endmodule

src/sim/adder_submodule_tb.sv
`timescale 1ns/1ps

module adder_submodule_tb;

    logic clk;
    logic reset;
    logic enable;
    logic [11:0] number1;
    logic [11:0] number2;
    logic [11:0] sum;
    logic valid;

    adder_submodule uut (
        .clk(clk),
        .reset(reset),
        .number1(number1),
        .number2(number2),
        .enable(enable),
        .sum_result(sum),
        .sum_state(valid)
    );

    always #18.52 clk = ~clk; // Periodo de 37.04 ns (27 MHz)

    // Proceso para la simulación
    initial begin
        $dumpfile("adder_submodule_tb.vcd");
        $dumpvars(0, adder_submodule_tb);

        clk = 0;
        reset = 1;
        enable = 0;
        number1 = 12'd0;
        number2 = 12'd0;

        #10;
        reset = 0;
        
        // Caso de prueba 1: Sumar 1000 + 2000
        number1 = 12'd367;
        number2 = 12'd980;
        enable = 1;
        #38;
        $display("Time: %0t, Number1: %0d, Number2: %0d, Sum: %0d, Valid: %b", 
        $time, number1, number2, sum, valid);
        enable = 0;
        #20;

        // Caso de prueba 2: Sumar 3000 + 1500
        number1 = 12'd300;
        number2 = 12'd157;
        enable = 1;
        #38;
        $display("Time: %0t, Number1: %0d, Number2: %0d, Sum: %0d, Valid: %b", 
        $time, number1, number2, sum, valid);
        enable = 0;
        #20;

        // Caso de prueba 3: Sumar 4095 + 4095 (máximo valor)
        number1 = 12'd999;
        number2 = 12'd850;
        enable = 1;
        #38;
        $display("Time: %0t, Number1: %0d, Number2: %0d, Sum: %0d, Valid: %b", 
        $time, number1, number2, sum, valid);
        enable = 0;
        #20;

        $finish;
    end

endmodule

src/build/adder_submodule_tb.vcd
$date
	Sat Sep 21 16:25:15 2024
$end
$version
	Icarus Verilog
$end
$timescale
	1ps
$end
$scope module adder_submodule_tb $end
$var wire 1 ! valid $end
$var wire 12 " sum [11:0] $end
$var reg 1 # clk $end
$var reg 1 $ enable $end
$var reg 12 % number1 [11:0] $end
$var reg 12 & number2 [11:0] $end
$var reg 1 ' reset $end
$scope module uut $end
$var wire 1 # clk $end
$var wire 1 $ enable $end
$var wire 12 ( number1 [11:0] $end
$var wire 12 ) number2 [11:0] $end
$var wire 1 ' reset $end
$var wire 1 ! sum_state $end
$var wire 12 * sum_result [11:0] $end
$var reg 1 + sum_ready $end
$var reg 14 , sum_reg [13:0] $end
$upscope $end
$upscope $end
$enddefinitions $end
$comment Show the parameter values. $end
$dumpall
$end
#0
$dumpvars
b0 ,
0+
b0 *
b0 )
b0 (
1'
b0 &
b0 %
0$
0#
b0 "
0!
$end
#10000
1$
b1111010100 &
b1111010100 )
b101101111 %
b101101111 (
0'
#18520
b10101000011 "
b10101000011 *
1!
1+
b10101000011 ,
1#
#37040
0#
#48000
0$
#55560
0!
0+
1#
#68000
1$
b10011101 &
b10011101 )
b100101100 %
b100101100 (
#74080
0#
#92600
b111001001 "
b111001001 *
1!
1+
b111001001 ,
1#
#106000
0$
#111120
0#
#126000
1$
b1101010010 &
b1101010010 )
b1111100111 %
b1111100111 (
#129640
b11100111001 "
b11100111001 *
b11100111001 ,
1#
#148160
0#
#164000
0$
#166680
0!
0+
1#
