src/design/teclado.sv
`timescale 1ns / 1ps

module teclado #(parameter S0=3'd0, S1=3'd1, S2=3'd2, S3=3'd3, S4=3'd4, S5=3'd5)(
    input rst,
    input clk,
    input [3:0] row,
    output logic [3:0] col,
    output logic [3:0] button
);

logic [2:0] state, next_state;
logic [7:0] key;

// Reset y estado inicial
always @(posedge rst) begin
    state <= S0; 
    next_state <= S0; 
    col <= 4'b1111; 
    button <= 4'b0000;
end

// Lógica de transición de estados
always @(posedge clk) begin
    if (!rst) begin
        state <= next_state;
    end
end

// Control de columnas
always @(state) begin
    case(state)
        S0: col = 4'b1111;
        S1: col = 4'b0001;
        S2: col = 4'b0010;
        S3: col = 4'b0100;
        S4: col = 4'b1000;
        S5: col = 4'b1111;
        default: col = 4'b1111;
    endcase
end

// Lógica de estados y lectura de filas
always @(row or state) begin
    case (state)
        S0: begin
            if (row != 4'b1111) begin // Si hay un botón presionado
                key[7:4] <= row;
                next_state <= S1;
            end else begin
                next_state <= S0;
            end
        end
        S1: begin
            if (row != 4'b1111) begin
                key[3:0] <= col;
                next_state <= S2;
            end else begin
                next_state <= S1;
            end
        end
        S2: begin
            if (row != 4'b1111) begin
                key[3:0] <= col;
                next_state <= S3;
            end else begin
                next_state <= S2;
            end
        end
        S3: begin
            if (row != 4'b1111) begin
                key[3:0] <= col;
                next_state <= S4;
            end else begin
                next_state <= S3;
            end
        end
        S4: begin
            if (row != 4'b1111) begin
                key[3:0] <= col;
                next_state <= S5;
            end else begin
                next_state <= S4;
            end
        end 
        S5: begin
            if (row == 4'b1111) begin
                next_state <= S0;
            end else begin
                next_state <= S5;
            end
        end
    endcase    
end

// Decodificación de botones
always @(posedge clk) begin
    if (state == S5 && row != 4'b1111) begin
        case (key)
            8'b00101000: button <= 4'd0; //Tecla 0
            8'b00010001: button <= 4'd0; //Tecla 1
            8'b00100001: button <= 4'd2; //Tecla 2
            8'b01000001: button <= 4'd3; //Tecla 3
            8'b00010010: button <= 4'd4; //Tecla 4
            8'b00100010: button <= 4'd5; //Tecla 5
            8'b01000010: button <= 4'd6; //Tecla 6
            8'b00010100: button <= 4'd7; //Tecla 7
            8'b00100100: button <= 4'd8; //Tecla 8
            8'b01000100: button <= 4'd9; //Tecla 9
            //8'b00010100: button <= 4'd10;
            //8'b01001000: button <= 4'd11;
            //8'b10000001: button <= 4'd12;
            //8'b10000010: button <= 4'd13;
            //8'b10000100: button <= 4'd14;
            //8'b10001000: button <= 4'd15;
            default: button <= 4'd0;
        endcase
    end
end 

endmodule

src/design/debounce.sv
module debounce (
    input clk,            
    input rst,            
    input btn_in,        
    output reg btn_out   
);
parameter DEBOUNCE_TIME = 20_000_000; // 20 ms para un reloj de 50 MHz
reg [31:0] counter;   
reg btn_in_d, btn_in_d2; 

always @(posedge clk) begin
    if (!rst) begin
        btn_in_d <= btn_in;  
        btn_in_d2 <= btn_in_d; 
    end else begin
        btn_in_d <= 1'b0; 
        btn_in_d2 <= 1'b0; 
    end
end

always @(posedge clk) begin
    if (!rst) begin
        if (btn_in_d2 == btn_in_d) begin
            if (counter < DEBOUNCE_TIME) begin
                counter <= counter + 1; 
            end else begin
                btn_out <= btn_in_d; 
            end
        end else begin
            counter <= 0; 
        end
    end else begin
        counter <= 0; 
        btn_out <= 1'b0; 
    end
end

endmodule

src/design/main.sv
`timescale 1ns / 1ps

module main #(
    parameter DEBOUNCE_TIME = 20_000_000 // Añade el parámetro aquí
)(
    input clk,                // Reloj del sistema
    input rst,                // Entrada de reset (activo en bajo)
    input [3:0] row,          // Entrada de filas del teclado (4 bits)
    output [3:0] col,         // Salida de columnas del teclado (4 bits)
    output [3:0] button       // Salida del botón (4 bits)
);

// Señales internas
logic [3:0] debounced_row;   // Señales de filas después de debounce

// Instancias del módulo debounce para cada fila
debounce #(
    .DEBOUNCE_TIME(DEBOUNCE_TIME)
) debounce_row0 (
    .clk(clk),
    .rst(rst),
    .btn_in(row[0]),
    .btn_out(debounced_row[0])
);

debounce #(
    .DEBOUNCE_TIME(DEBOUNCE_TIME)
) debounce_row1 (
    .clk(clk),
    .rst(rst),
    .btn_in(row[1]),
    .btn_out(debounced_row[1])
);

debounce #(
    .DEBOUNCE_TIME(DEBOUNCE_TIME)
) debounce_row2 (
    .clk(clk),
    .rst(rst),
    .btn_in(row[2]),
    .btn_out(debounced_row[2])
);

debounce #(
    .DEBOUNCE_TIME(DEBOUNCE_TIME)
) debounce_row3 (
    .clk(clk),
    .rst(rst),
    .btn_in(row[3]),
    .btn_out(debounced_row[3])
);

// Instancias de los módulos teclado
teclado keypad_encoder (
    .rst(rst),
    .clk(clk),
    .row(debounced_row), // Usa las filas debounced
    .col(col),           // Salida de las columnas del teclado
    .button(button)      // Salida del botón
);

endmodule

src/sim/main_tb.sv
`timescale 1ns / 1ps

module main_tb;

// Parámetros del reloj
parameter CLK_PERIOD = 10; // Período del reloj en nanosegundos
parameter DEBOUNCE_TIME = 20_000_000; // Tiempo de debounce
// Señales del testbench
logic clk;
logic rst;
logic [3:0] row;
logic [3:0] col;
logic [3:0] button;

// Instancia del módulo principal
main #(
    .DEBOUNCE_TIME(DEBOUNCE_TIME)
) uut (
    .clk(clk),
    .rst(rst),
    .row(row),
    .col(col),
    .button(button)
);

// Generador del reloj
initial begin
    clk = 0;
    forever #(CLK_PERIOD / 2) clk = ~clk;
end

// Generador del reset y estímulo
initial begin
    $dumpfile("simulation.vcd"); // Nombre del archivo VCD
    $dumpvars(0, main_tb);        // Registrar todas las señales en el módulo tb_main

    rst = 1;
    row = 4'b1111; // Inicializa row como 1111
    #100; // Mantener reset activo por 100 ns
    rst = 0;

    // Prueba de botones
    // Prueba con fila 0 (row[0])
    #50 row = 4'b1110; // Simula presión de botón en la primera fila
    #200 row = 4'b1111; // Liberar botón
    #100; // Esperar

    // Prueba con fila 1 (row[1])
    #50 row = 4'b1101; // Simula presión de botón en la segunda fila
    #200 row = 4'b1111; // Liberar botón
    #100; // Esperar

    // Prueba con fila 2 (row[2])
    #50 row = 4'b1011; // Simula presión de botón en la tercera fila
    #200 row = 4'b1111; // Liberar botón
    #100; // Esperar

    // Prueba con fila 3 (row[3])
    #50 row = 4'b0111; // Simula presión de botón en la cuarta fila
    #200 row = 4'b1111; // Liberar botón
    #100; // Esperar

    // Finalizar simulación
    #100;
    $finish;
end

// Monitoreo de señales
initial begin
    $monitor("Time = %0t, row = %b, col = %b, button = %b", $time, row, col, button);
end

endmodule

src/build/simulation.vcd
$date
	Sat Sep 21 20:43:39 2024
$end
$version
	Icarus Verilog
$end
$timescale
	1ps
$end
$scope module main_tb $end
$var wire 4 ! col [3:0] $end
$var wire 4 " button [3:0] $end
$var parameter 32 # CLK_PERIOD $end
$var parameter 32 $ DEBOUNCE_TIME $end
$var reg 1 % clk $end
$var reg 4 & row [3:0] $end
$var reg 1 ' rst $end
$scope module uut $end
$var wire 1 % clk $end
$var wire 4 ( row [3:0] $end
$var wire 1 ' rst $end
$var wire 4 ) debounced_row [3:0] $end
$var wire 4 * col [3:0] $end
$var wire 4 + button [3:0] $end
$var parameter 32 , DEBOUNCE_TIME $end
$scope module debounce_row0 $end
$var wire 1 - btn_in $end
$var wire 1 % clk $end
$var wire 1 ' rst $end
$var parameter 32 . DEBOUNCE_TIME $end
$var reg 1 / btn_in_d $end
$var reg 1 0 btn_in_d2 $end
$var reg 1 1 btn_out $end
$var reg 32 2 counter [31:0] $end
$upscope $end
$scope module debounce_row1 $end
$var wire 1 3 btn_in $end
$var wire 1 % clk $end
$var wire 1 ' rst $end
$var parameter 32 4 DEBOUNCE_TIME $end
$var reg 1 5 btn_in_d $end
$var reg 1 6 btn_in_d2 $end
$var reg 1 7 btn_out $end
$var reg 32 8 counter [31:0] $end
$upscope $end
$scope module debounce_row2 $end
$var wire 1 9 btn_in $end
$var wire 1 % clk $end
$var wire 1 ' rst $end
$var parameter 32 : DEBOUNCE_TIME $end
$var reg 1 ; btn_in_d $end
$var reg 1 < btn_in_d2 $end
$var reg 1 = btn_out $end
$var reg 32 > counter [31:0] $end
$upscope $end
$scope module debounce_row3 $end
$var wire 1 ? btn_in $end
$var wire 1 % clk $end
$var wire 1 ' rst $end
$var parameter 32 @ DEBOUNCE_TIME $end
$var reg 1 A btn_in_d $end
$var reg 1 B btn_in_d2 $end
$var reg 1 C btn_out $end
$var reg 32 D counter [31:0] $end
$upscope $end
$scope module keypad_encoder $end
$var wire 1 % clk $end
$var wire 4 E row [3:0] $end
$var wire 1 ' rst $end
$var parameter 3 F S0 $end
$var parameter 3 G S1 $end
$var parameter 3 H S2 $end
$var parameter 3 I S3 $end
$var parameter 3 J S4 $end
$var parameter 3 K S5 $end
$var reg 4 L button [3:0] $end
$var reg 4 M col [3:0] $end
$var reg 8 N key [7:0] $end
$var reg 3 O next_state [2:0] $end
$var reg 3 P state [2:0] $end
$upscope $end
$upscope $end
$upscope $end
$enddefinitions $end
$comment Show the parameter values. $end
$dumpall
b101 K
b100 J
b11 I
b10 H
b1 G
b0 F
b1001100010010110100000000 @
b1001100010010110100000000 :
b1001100010010110100000000 4
b1001100010010110100000000 .
b1001100010010110100000000 ,
b1001100010010110100000000 $
b1010 #
$end
#0
$dumpvars
b0 P
b0 O
bx N
b1111 M
b0 L
bx E
bx D
xC
xB
xA
1?
bx >
x=
x<
x;
19
bx 8
x7
x6
x5
13
bx 2
x1
x0
x/
1-
b0 +
b1111 *
bx )
b1111 (
1'
b1111 &
0%
b0 "
b1111 !
$end
#5000
b1 O
b0xxxx N
00
0/
01
b0 2
06
05
07
b0 8
0<
0;
0=
b0 >
0B
0A
b0 )
b0 E
0C
b0 D
1%
#10000
0%
#15000
1%
#20000
0%
#25000
1%
#30000
0%
#35000
1%
#40000
0%
#45000
1%
#50000
0%
#55000
1%
#60000
0%
#65000
1%
#70000
0%
#75000
1%
#80000
0%
#85000
1%
#90000
0%
#95000
1%
#100000
0%
0'
#105000
b10 O
b1 N
b1 !
b1 *
b1 M
1/
b1 2
15
b1 8
1;
b1 >
1A
b1 D
b1 P
1%
#110000
0%
#115000
b11 O
b10 N
b10 !
b10 *
b10 M
b10 P
b0 D
1B
b0 >
1<
b0 8
16
b0 2
10
1%
#120000
0%
#125000
b100 O
b100 N
b100 !
b100 *
b100 M
b1 2
b1 8
b1 >
b1 D
b11 P
1%
#130000
0%
#135000
b101 O
b1000 N
b1000 !
b1000 *
b1000 M
b100 P
b10 D
b10 >
b10 8
b10 2
1%
#140000
0%
#145000
b1111 !
b1111 *
b1111 M
b11 2
b11 8
b11 >
b11 D
b101 P
1%
#150000
0-
0%
b1110 &
b1110 (
#155000
b100 D
b100 >
b100 8
b100 2
0/
1%
#160000
0%
#165000
00
b0 2
b101 8
b101 >
b101 D
1%
#170000
0%
#175000
b110 D
b110 >
b110 8
b1 2
1%
#180000
0%
#185000
b10 2
b111 8
b111 >
b111 D
1%
#190000
0%
#195000
b1000 D
b1000 >
b1000 8
b11 2
1%
#200000
0%
#205000
b100 2
b1001 8
b1001 >
b1001 D
1%
#210000
0%
#215000
b1010 D
b1010 >
b1010 8
b101 2
1%
#220000
0%
#225000
b110 2
b1011 8
b1011 >
b1011 D
1%
#230000
0%
#235000
b1100 D
b1100 >
b1100 8
b111 2
1%
#240000
0%
#245000
b1000 2
b1101 8
b1101 >
b1101 D
1%
#250000
0%
#255000
b1110 D
b1110 >
b1110 8
b1001 2
1%
#260000
0%
#265000
b1010 2
b1111 8
b1111 >
b1111 D
1%
#270000
0%
#275000
b10000 D
b10000 >
b10000 8
b1011 2
1%
#280000
0%
#285000
b1100 2
b10001 8
b10001 >
b10001 D
1%
#290000
0%
#295000
b10010 D
b10010 >
b10010 8
b1101 2
1%
#300000
0%
#305000
b1110 2
b10011 8
b10011 >
b10011 D
1%
#310000
0%
#315000
b10100 D
b10100 >
b10100 8
b1111 2
1%
#320000
0%
#325000
b10000 2
b10101 8
b10101 >
b10101 D
1%
#330000
0%
#335000
b10110 D
b10110 >
b10110 8
b10001 2
1%
#340000
0%
#345000
b10010 2
b10111 8
b10111 >
b10111 D
1%
#350000
1-
0%
b1111 &
b1111 (
#355000
b11000 D
b11000 >
b11000 8
b10011 2
1/
1%
#360000
0%
#365000
10
b0 2
b11001 8
b11001 >
b11001 D
1%
#370000
0%
#375000
b11010 D
b11010 >
b11010 8
b1 2
1%
#380000
0%
#385000
b10 2
b11011 8
b11011 >
b11011 D
1%
#390000
0%
#395000
b11100 D
b11100 >
b11100 8
b11 2
1%
#400000
0%
#405000
b100 2
b11101 8
b11101 >
b11101 D
1%
#410000
0%
#415000
b11110 D
b11110 >
b11110 8
b101 2
1%
#420000
0%
#425000
b110 2
b11111 8
b11111 >
b11111 D
1%
#430000
0%
#435000
b100000 D
b100000 >
b100000 8
b111 2
1%
#440000
0%
#445000
b1000 2
b100001 8
b100001 >
b100001 D
1%
#450000
0%
#455000
b100010 D
b100010 >
b100010 8
b1001 2
1%
#460000
0%
#465000
b1010 2
b100011 8
b100011 >
b100011 D
1%
#470000
0%
#475000
b100100 D
b100100 >
b100100 8
b1011 2
1%
#480000
0%
#485000
b1100 2
b100101 8
b100101 >
b100101 D
1%
#490000
0%
#495000
b100110 D
b100110 >
b100110 8
b1101 2
1%
#500000
03
0%
b1101 &
b1101 (
#505000
b1110 2
05
b100111 8
b100111 >
b100111 D
1%
#510000
0%
#515000
b101000 D
b101000 >
b0 8
06
b1111 2
1%
#520000
0%
#525000
b10000 2
b1 8
b101001 >
b101001 D
1%
#530000
0%
#535000
b101010 D
b101010 >
b10 8
b10001 2
1%
#540000
0%
#545000
b10010 2
b11 8
b101011 >
b101011 D
1%
#550000
0%
#555000
b101100 D
b101100 >
b100 8
b10011 2
1%
#560000
0%
#565000
b10100 2
b101 8
b101101 >
b101101 D
1%
#570000
0%
#575000
b101110 D
b101110 >
b110 8
b10101 2
1%
#580000
0%
#585000
b10110 2
b111 8
b101111 >
b101111 D
1%
#590000
0%
#595000
b110000 D
b110000 >
b1000 8
b10111 2
1%
#600000
0%
#605000
b11000 2
b1001 8
b110001 >
b110001 D
1%
#610000
0%
#615000
b110010 D
b110010 >
b1010 8
b11001 2
1%
#620000
0%
#625000
b11010 2
b1011 8
b110011 >
b110011 D
1%
#630000
0%
#635000
b110100 D
b110100 >
b1100 8
b11011 2
1%
#640000
0%
#645000
b11100 2
b1101 8
b110101 >
b110101 D
1%
#650000
0%
#655000
b110110 D
b110110 >
b1110 8
b11101 2
1%
#660000
0%
#665000
b11110 2
b1111 8
b110111 >
b110111 D
1%
#670000
0%
#675000
b111000 D
b111000 >
b10000 8
b11111 2
1%
#680000
0%
#685000
b100000 2
b10001 8
b111001 >
b111001 D
1%
#690000
0%
#695000
b111010 D
b111010 >
b10010 8
b100001 2
1%
#700000
13
0%
b1111 &
b1111 (
#705000
b100010 2
15
b10011 8
b111011 >
b111011 D
1%
#710000
0%
#715000
b111100 D
b111100 >
b0 8
16
b100011 2
1%
#720000
0%
#725000
b100100 2
b1 8
b111101 >
b111101 D
1%
#730000
0%
#735000
b111110 D
b111110 >
b10 8
b100101 2
1%
#740000
0%
#745000
b100110 2
b11 8
b111111 >
b111111 D
1%
#750000
0%
#755000
b1000000 D
b1000000 >
b100 8
b100111 2
1%
#760000
0%
#765000
b101000 2
b101 8
b1000001 >
b1000001 D
1%
#770000
0%
#775000
b1000010 D
b1000010 >
b110 8
b101001 2
1%
#780000
0%
#785000
b101010 2
b111 8
b1000011 >
b1000011 D
1%
#790000
0%
#795000
b1000100 D
b1000100 >
b1000 8
b101011 2
1%
#800000
0%
#805000
b101100 2
b1001 8
b1000101 >
b1000101 D
1%
#810000
0%
#815000
b1000110 D
b1000110 >
b1010 8
b101101 2
1%
#820000
0%
#825000
b101110 2
b1011 8
b1000111 >
b1000111 D
1%
#830000
0%
#835000
b1001000 D
b1001000 >
b1100 8
b101111 2
1%
#840000
0%
#845000
b110000 2
b1101 8
b1001001 >
b1001001 D
1%
#850000
09
0%
b1011 &
b1011 (
#855000
b1001010 D
b1001010 >
0;
b1110 8
b110001 2
1%
#860000
0%
#865000
b110010 2
b1111 8
0<
b0 >
b1001011 D
1%
#870000
0%
#875000
b1001100 D
b1 >
b10000 8
b110011 2
1%
#880000
0%
#885000
b110100 2
b10001 8
b10 >
b1001101 D
1%
#890000
0%
#895000
b1001110 D
b11 >
b10010 8
b110101 2
1%
#900000
0%
#905000
b110110 2
b10011 8
b100 >
b1001111 D
1%
#910000
0%
#915000
b1010000 D
b101 >
b10100 8
b110111 2
1%
#920000
0%
#925000
b111000 2
b10101 8
b110 >
b1010001 D
1%
#930000
0%
#935000
b1010010 D
b111 >
b10110 8
b111001 2
1%
#940000
0%
#945000
b111010 2
b10111 8
b1000 >
b1010011 D
1%
#950000
0%
#955000
b1010100 D
b1001 >
b11000 8
b111011 2
1%
#960000
0%
#965000
b111100 2
b11001 8
b1010 >
b1010101 D
1%
#970000
0%
#975000
b1010110 D
b1011 >
b11010 8
b111101 2
1%
#980000
0%
#985000
b111110 2
b11011 8
b1100 >
b1010111 D
1%
#990000
0%
#995000
b1011000 D
b1101 >
b11100 8
b111111 2
1%
#1000000
0%
#1005000
b1000000 2
b11101 8
b1110 >
b1011001 D
1%
#1010000
0%
#1015000
b1011010 D
b1111 >
b11110 8
b1000001 2
1%
#1020000
0%
#1025000
b1000010 2
b11111 8
b10000 >
b1011011 D
1%
#1030000
0%
#1035000
b1011100 D
b10001 >
b100000 8
b1000011 2
1%
#1040000
0%
#1045000
b1000100 2
b100001 8
b10010 >
b1011101 D
1%
#1050000
19
0%
b1111 &
b1111 (
#1055000
b1011110 D
b10011 >
1;
b100010 8
b1000101 2
1%
#1060000
0%
#1065000
b1000110 2
b100011 8
1<
b0 >
b1011111 D
1%
#1070000
0%
#1075000
b1100000 D
b1 >
b100100 8
b1000111 2
1%
#1080000
0%
#1085000
b1001000 2
b100101 8
b10 >
b1100001 D
1%
#1090000
0%
#1095000
b1100010 D
b11 >
b100110 8
b1001001 2
1%
#1100000
0%
#1105000
b1001010 2
b100111 8
b100 >
b1100011 D
1%
#1110000
0%
#1115000
b1100100 D
b101 >
b101000 8
b1001011 2
1%
#1120000
0%
#1125000
b1001100 2
b101001 8
b110 >
b1100101 D
1%
#1130000
0%
#1135000
b1100110 D
b111 >
b101010 8
b1001101 2
1%
#1140000
0%
#1145000
b1001110 2
b101011 8
b1000 >
b1100111 D
1%
#1150000
0%
#1155000
b1101000 D
b1001 >
b101100 8
b1001111 2
1%
#1160000
0%
#1165000
b1010000 2
b101101 8
b1010 >
b1101001 D
1%
#1170000
0%
#1175000
b1101010 D
b1011 >
b101110 8
b1010001 2
1%
#1180000
0%
#1185000
b1010010 2
b101111 8
b1100 >
b1101011 D
1%
#1190000
0%
#1195000
b1101100 D
b1101 >
b110000 8
b1010011 2
1%
#1200000
0?
0%
b111 &
b111 (
#1205000
b1010100 2
b110001 8
b1110 >
0A
b1101101 D
1%
#1210000
0%
#1215000
b0 D
0B
b1111 >
b110010 8
b1010101 2
1%
#1220000
0%
#1225000
b1010110 2
b110011 8
b10000 >
b1 D
1%
#1230000
0%
#1235000
b10 D
b10001 >
b110100 8
b1010111 2
1%
#1240000
0%
#1245000
b1011000 2
b110101 8
b10010 >
b11 D
1%
#1250000
0%
#1255000
b100 D
b10011 >
b110110 8
b1011001 2
1%
#1260000
0%
#1265000
b1011010 2
b110111 8
b10100 >
b101 D
1%
#1270000
0%
#1275000
b110 D
b10101 >
b111000 8
b1011011 2
1%
#1280000
0%
#1285000
b1011100 2
b111001 8
b10110 >
b111 D
1%
#1290000
0%
#1295000
b1000 D
b10111 >
b111010 8
b1011101 2
1%
#1300000
0%
#1305000
b1011110 2
b111011 8
b11000 >
b1001 D
1%
#1310000
0%
#1315000
b1010 D
b11001 >
b111100 8
b1011111 2
1%
#1320000
0%
#1325000
b1100000 2
b111101 8
b11010 >
b1011 D
1%
#1330000
0%
#1335000
b1100 D
b11011 >
b111110 8
b1100001 2
1%
#1340000
0%
#1345000
b1100010 2
b111111 8
b11100 >
b1101 D
1%
#1350000
0%
#1355000
b1110 D
b11101 >
b1000000 8
b1100011 2
1%
#1360000
0%
#1365000
b1100100 2
b1000001 8
b11110 >
b1111 D
1%
#1370000
0%
#1375000
b10000 D
b11111 >
b1000010 8
b1100101 2
1%
#1380000
0%
#1385000
b1100110 2
b1000011 8
b100000 >
b10001 D
1%
#1390000
0%
#1395000
b10010 D
b100001 >
b1000100 8
b1100111 2
1%
#1400000
1?
0%
b1111 &
b1111 (
#1405000
b1101000 2
b1000101 8
b100010 >
1A
b10011 D
1%
#1410000
0%
#1415000
b0 D
1B
b100011 >
b1000110 8
b1101001 2
1%
#1420000
0%
#1425000
b1101010 2
b1000111 8
b100100 >
b1 D
1%
#1430000
0%
#1435000
b10 D
b100101 >
b1001000 8
b1101011 2
1%
#1440000
0%
#1445000
b1101100 2
b1001001 8
b100110 >
b11 D
1%
#1450000
0%
#1455000
b100 D
b100111 >
b1001010 8
b1101101 2
1%
#1460000
0%
#1465000
b1101110 2
b1001011 8
b101000 >
b101 D
1%
#1470000
0%
#1475000
b110 D
b101001 >
b1001100 8
b1101111 2
1%
#1480000
0%
#1485000
b1110000 2
b1001101 8
b101010 >
b111 D
1%
#1490000
0%
#1495000
b1000 D
b101011 >
b1001110 8
b1110001 2
1%
#1500000
0%
#1505000
b1110010 2
b1001111 8
b101100 >
b1001 D
1%
#1510000
0%
#1515000
b1010 D
b101101 >
b1010000 8
b1110011 2
1%
#1520000
0%
#1525000
b1110100 2
b1010001 8
b101110 >
b1011 D
1%
#1530000
0%
#1535000
b1100 D
b101111 >
b1010010 8
b1110101 2
1%
#1540000
0%
#1545000
b1110110 2
b1010011 8
b110000 >
b1101 D
1%
#1550000
0%
#1555000
b1110 D
b110001 >
b1010100 8
b1110111 2
1%
#1560000
0%
#1565000
b1111000 2
b1010101 8
b110010 >
b1111 D
1%
#1570000
0%
#1575000
b10000 D
b110011 >
b1010110 8
b1111001 2
1%
#1580000
0%
#1585000
b1111010 2
b1010111 8
b110100 >
b10001 D
1%
#1590000
0%
#1595000
b10010 D
b110101 >
b1011000 8
b1111011 2
1%
